correios_utils/__init__.py
correios_utils/correios.py
correios_utils-0.1.2.dist-info/LICENSE
correios_utils-0.1.2.dist-info/WHEEL
correios_utils-0.1.2.dist-info/METADATA
correios_utils-0.1.2.dist-info/RECORD
