Metadata-Version: 2.1
Name: correios-utils
Version: 0.1.2
Summary: 
License: MIT
Author: Douglas Gusson
Author-email: douglasgusson@gmail.com
Requires-Python: >=3.6.1,<4.0.0
Classifier: License :: OSI Approved :: MIT License
Classifier: Programming Language :: Python :: 3
Classifier: Programming Language :: Python :: 3.10
Classifier: Programming Language :: Python :: 3.7
Classifier: Programming Language :: Python :: 3.8
Classifier: Programming Language :: Python :: 3.9
Requires-Dist: requests (>=2.27.1,<3.0.0)
Requires-Dist: xmltodict (>=0.12.0,<0.13.0)
